{
  "name": "True Dark",
  "dark": true,
  "author": "Ahmed Elshaer",
  "editorScheme": "/TrueDark.xml",
  "colors": {
    "primary": "#121212",
    "secondary": "#121212",
    "activeSelection": "#2D2D2D",
    "inactiveSelection": "#1F1F1F",
    "borderColor": "#121212",
    "separatorColor": "#1F1F1F"
  },
  "ui": {
    "*": {
      "arc": "6",
      "background": "primary",
      "selectionBackground": "activeSelection",
      "selectionInactiveBackground": "inactiveSelection",
      "disabledBackground": "primary",
      "underlineColor": "activeSelection",
      "borderColor": "borderColor",
      "separatorColor": "separatorColor"
    },
    "ActionButton": {
      "hoverBorderColor": "activeSelection",
      "hoverBackground": "secondary",
      "pressedBorderColor": "inactiveSelection",
      "pressedBackground": "secondary"
    },
    "Bookmark": {
      "Mnemonic": {
      }
    },
    "BookmarkMnemonicAssigned": {
      "background": "inactiveSelection",
      "borderColor": "inactiveSelection"
    },
    "BookmarkMnemonicCurrent": {
      "background": "activeSelection",
      "borderColor": "activeSelection"
    },
    "Borders": {
      "color": "borderColor",
      "ContrastBorderColor": "borderColor"
    },
    "Button": {
      "foreground": "#D1D1D1",
      "startBackground": "secondary",
      "endBackground": "secondary",
      "focusedBorderColor": "inactiveSelection",
      "startBorderColor": "inactiveSelection",
      "endBorderColor": "inactiveSelection",
      "default": {
        "foreground": "#D1D1D1",
        "startBackground": "secondary",
        "endBackground": "secondary",
        "startBorderColor": "#D1D1D1",
        "endBorderColor": "#D1D1D1",
        "focusColor": "secondary",
        "focusedBorderColor": "#D1D1D1"
      }
    },
    "Counter": {
      "foreground": "#D1D1D1"
    },
    "TextField": {
      "background": "primary"
    },
    "ComboBox": {
      "nonEditableBackground": "secondary",
      "ArrowButton": {
        "background": "secondary",
        "nonEditableBackground": "secondary"
      }
    },
    "CompletionPopup": {
      "matchForeground": "#fc5fa3",
      "selectionBackground": "activeSelection",
      "background": "primary",
      "borderColor": "borderColor"
    },
    "Component": {
      "focusColor": "activeSelection",
      "focusedBorderColor": "activeSelection",
      "disabledBorderColor": "borderColor"
    },
    "Editor": {
      "shortcutForeground": "activeSelection",
      "background": "secondary",
      "SearchField.borderColor": "borderColor",
      "Tooltip.background": "inactiveSelection",
      "Tooltip.borderColor": "borderColor",
      "currentLineHighlight.style": "rounded",
      "lineHighlight.borderRadius": 6,
      "caretRow.style": "rounded"
    },
    "EditorTabs": {
      "underlinedTabBackground": "primary",
      "background": "secondary",
      "underlineHeight": 2,
      "tabArc": 6
    },
    "Link": {
      "activeForeground": "#0c90f8",
      "hoverForeground": "#9a61cb",
      "visitedForeground": "#0c90f8",
      "pressedForeground": "#9a61cb"
    },
    "Notification": {
      "ToolWindow": {
        "informativeBackground": "primary",
        "informativeBorderColor": "#42b827",
        "informativeForeground": "#D1D1D1",
        "warningBackground": "primary",
        "errorBackground": "primary"
      }
    },
    "Plugins": {
      "hoverBackground": "activeSelection",
      "lightSelectionBackground": "activeSelection"
    },
    "PasswordField": {
      "background": "secondary"
    },
    "SearchMatch": {
      "startBackground": "#eeed38",
      "endBackground": "#eeed38"
    },
    "SearchEverywhere": {
      "Tab": {
        "selectedBackground": "inactiveSelection"
      }
    },
    "SidePanel": {
      "background": "secondary"
    },
    "StatusBar": {
      "hoverBackground": "secondary"
    },
    "Table": {
      "hoverBackground": "inactiveSelection",
      "lightSelectionBackground": "activeSelection"
    },
    "TableHeader": {
      "bottomSeparatorColor": "separatorColor"
    },
    "ToggleButton": {
      "onBackground": "#D1D1D1"
    },
    "ToolWindow": {
      "Button": {
        "selectedBackground": "secondary"
      },
      "Header": {
        "background": "primary",
        "inactiveBackground": "secondary"
      }
    },
    "Tree": {
      "background": "primary",
      "selectionBackground": "activeSelection",
      "selectionInactiveBackground": "inactiveSelection",
      "foreground": "#D1D1D1",
      "rowHeight": 22
    },
    "VersionControl": {
      "Log": {
        "Commit": {
          "currentBranchBackground": "secondary",
          "hoveredBackground": "inactiveSelection"
        }
      }
    },
    "WelcomeScreen": {
      "SidePanel": {
        "background": "secondary"
      },
      "Projects": {
        "background": "inactiveSelection",
        "actions": {
          "background": "inactiveSelection"
        }
      }
    },
    "FileColor": {
      "Yellow": "121212",
      "Green": "121212",
      "Blue": "121212",
      "Violet": "121212",
      "Orange": "121212",
      "Rose": "121212"
    },
    "ProjectView": {
      "background": "primary",
      "selectionBackground": "activeSelection",
      "selectionInactiveBackground": "inactiveSelection"
    },
    "FileColors": {
      "enabledForTabs": false,
      "enabledForProjectView": false
    },
    "Scope": {
      "background": "primary"
    },
    "Popup": {
      "background": "primary",
      "Header.activeBackground": "activeSelection",
      "Header.inactiveBackground": "inactiveSelection",
      "separatorColor": "borderColor",
      "borderColor": "borderColor",
      "Advertiser": {
        "background": "inactiveSelection",
        "borderColor": "borderColor"
      }
    },
    "Breadcrumbs": {
      "background": "primary",
      "selectionBackground": "activeSelection",
      "hoverBackground": "inactiveSelection",
      "borderColor": "borderColor"
    },
    "Menu": {
      "background": "primary",
      "foreground": "#D1D1D1",
      "separatorColor": "borderColor",
      "borderColor": "borderColor",
      "selectionBackground": "activeSelection"
    },
    "CheckBox": {
      "background": "primary",
      "foreground": "#D1D1D1",
      "select": "#D1D1D1"
    },
    "RadioButton": {
      "background": "primary", 
      "foreground": "#D1D1D1",
      "select": "#D1D1D1"
    },
    "FormattedTextField": {
      "background": "secondary",
      "caretForeground": "#D1D1D1"
    },
    "TextArea": {
      "background": "secondary",
      "caretForeground": "#D1D1D1",
      "selectionBackground": "activeSelection"
    },
    "TextPane": {
      "background": "secondary",
      "caretForeground": "#D1D1D1",
      "selectionBackground": "activeSelection"
    }
  },
  "icons": {
    "ColorPalette": {
      "Actions.Red": "#c63a5d",
      "Actions.Yellow": "#caba2d",
      "Actions.Green": "#25ad6b",
      "Actions.Blue": "#4d85ff",
      "Objects.RedStatus": "#dd3962",
      "Objects.Red": "#c63a5d",
      "Objects.Pink": "#f98b9e",
      "Objects.Yellow": "#caba2d",
      "Objects.Green": "#239e62",
      "Objects.Blue": "#598bff",
      "Objects.Purple": "#af71e0",
      "Objects.BlackText": "#000000ff",
      "Objects.YellowDark": "#988c26",
      "Objects.GreenAndroid": "#78c257",
      "Checkbox.Border.Default": "#121212",
      "Checkbox.Border.Default.Dark": "#121212",
      "Checkbox.Background.Default": "#343333",
      "Checkbox.Background.Default.Dark": "#343333",
      "Checkbox.Background.Disabled": "#212327",
      "Checkbox.Background.Disabled.Dark": "#212327",
      "Checkbox.Focus.Wide": "#2f55b1",
      "Checkbox.Focus.Wide.Dark": "#2f55b1"
    }
  }
}
